SDP18/Driver_code_GA.py
SDP18/Driver_code_HCO.py
SDP18/Driver_code_SA.py
SDP18/Driver_code_TS.py
SDP18/Generate_initial_solution.py
SDP18/MO_fitting_func_calc.py
SDP18/__init__.py
SDP18/find_legal_neighbors.py
SDP18/genetic_algo_functions.py
SDP18/login_page.py
SDP18/login_page_v2.py
SDP18/output_table.py
SDP18/plot_pareto_front.py
SDP18/read_MAS.py
SDP18/read_csv.py
SDP18/read_csv_old.py
SDP18/read_toschedule.py
SDP18/read_toschedule_old.py
SDP18/soln_representation_concept.py
SDP18/swapper.py
SDP18/test_ga.py
SDP18/test_gui.py
SDP18/test_hco.py
SDP18/test_sa.py
SDP18/test_ts.py
SDP18/view_timetable.py
SDP18/view_timetable1.py
SDP18/view_timetable_old.py
SDP18/view_tooltip.py
SDP18_meta/Driver_code_GA.py
SDP18_meta/Driver_code_HCO.py
SDP18_meta/Driver_code_SA.py
SDP18_meta/Driver_code_TS.py
SDP18_meta/Generate_initial_solution.py
SDP18_meta/MO_fitting_func_calc.py
SDP18_meta/__init__.py
SDP18_meta/find_legal_neighbors.py
SDP18_meta/genetic_algo_functions.py
SDP18_meta/login_page.py
SDP18_meta/login_page_v2.py
SDP18_meta/output_table.py
SDP18_meta/plot_pareto_front.py
SDP18_meta/read_MAS.py
SDP18_meta/read_csv.py
SDP18_meta/read_csv_old.py
SDP18_meta/read_toschedule.py
SDP18_meta/read_toschedule_old.py
SDP18_meta/soln_representation_concept.py
SDP18_meta/swapper.py
SDP18_meta/test_ga.py
SDP18_meta/test_gui.py
SDP18_meta/test_hco.py
SDP18_meta/test_sa.py
SDP18_meta/test_ts.py
SDP18_meta/view_timetable.py
SDP18_meta/view_timetable1.py
SDP18_meta/view_timetable_old.py
SDP18_meta/view_tooltip.py
main/Driver_code_GA.py
main/Driver_code_HCO.py
main/Driver_code_SA.py
main/Driver_code_TS.py
main/Generate_initial_solution.py
main/MO_fitting_func_calc.py
main/__init__.py
main/find_legal_neighbors.py
main/genetic_algo_functions.py
main/login_page.py
main/login_page_v2.py
main/output_table.py
main/plot_pareto_front.py
main/read_MAS.py
main/read_csv.py
main/read_csv_old.py
main/read_toschedule.py
main/read_toschedule_old.py
main/soln_representation_concept.py
main/swapper.py
SDP18-0.1.0.dist-info/LICENCE.txt
SDP18-0.1.0.dist-info/METADATA
SDP18-0.1.0.dist-info/WHEEL
SDP18-0.1.0.dist-info/top_level.txt
SDP18-0.1.0.dist-info/RECORD
