Metadata-Version: 2.1
Name: SDP18
Version: 0.1.0
Summary: This package schedules surgeries using metaheurisitcs. It is a project done for in NUS for Systems Design Project (SDP):Metaheuristic Surgery Scheduling for Operating Theatre Scheduling
Home-page: https://github.com/lwq96/NewProject
Author: SDP18
Author-email: e0176071@u.nus.edu
License: MIT
Keywords: metaheuristic,surgery,scheduling
Platform: UNKNOWN
Classifier: Development Status :: 5 - Production/Stable
Classifier: Intended Audience :: Education
Classifier: Operating System :: Microsoft :: Windows :: Windows 10
Classifier: License :: OSI Approved :: MIT License
Classifier: Programming Language :: Python :: 3
